MANIFEST.in
README
requirements.txt
setup.py
ajenti.plugin.docker.egg-info/PKG-INFO
ajenti.plugin.docker.egg-info/SOURCES.txt
ajenti.plugin.docker.egg-info/dependency_links.txt
ajenti.plugin.docker.egg-info/top_level.txt
ajenti_plugin_docker/README.md
ajenti_plugin_docker/__init__.py
ajenti_plugin_docker/main.py
ajenti_plugin_docker/plugin.yml
ajenti_plugin_docker/requirements.txt
ajenti_plugin_docker/views.py
ajenti_plugin_docker/locale/app.pot
ajenti_plugin_docker/locale/af/LC_MESSAGES/app.js
ajenti_plugin_docker/locale/af/LC_MESSAGES/app.po
ajenti_plugin_docker/locale/ar/LC_MESSAGES/app.js
ajenti_plugin_docker/locale/ar/LC_MESSAGES/app.po
ajenti_plugin_docker/locale/be/LC_MESSAGES/app.js
ajenti_plugin_docker/locale/be/LC_MESSAGES/app.po
ajenti_plugin_docker/locale/bg/LC_MESSAGES/app.js
ajenti_plugin_docker/locale/bg/LC_MESSAGES/app.po
ajenti_plugin_docker/locale/bn/LC_MESSAGES/app.js
ajenti_plugin_docker/locale/bn/LC_MESSAGES/app.po
ajenti_plugin_docker/locale/bs/LC_MESSAGES/app.js
ajenti_plugin_docker/locale/bs/LC_MESSAGES/app.po
ajenti_plugin_docker/locale/ca/LC_MESSAGES/app.js
ajenti_plugin_docker/locale/ca/LC_MESSAGES/app.po
ajenti_plugin_docker/locale/cs/LC_MESSAGES/app.js
ajenti_plugin_docker/locale/cs/LC_MESSAGES/app.po
ajenti_plugin_docker/locale/da/LC_MESSAGES/app.js
ajenti_plugin_docker/locale/da/LC_MESSAGES/app.po
ajenti_plugin_docker/locale/de/LC_MESSAGES/app.js
ajenti_plugin_docker/locale/de/LC_MESSAGES/app.po
ajenti_plugin_docker/locale/el/LC_MESSAGES/app.js
ajenti_plugin_docker/locale/el/LC_MESSAGES/app.po
ajenti_plugin_docker/locale/en/LC_MESSAGES/app.po
ajenti_plugin_docker/locale/eo/LC_MESSAGES/app.js
ajenti_plugin_docker/locale/eo/LC_MESSAGES/app.po
ajenti_plugin_docker/locale/es-ES/LC_MESSAGES/app.js
ajenti_plugin_docker/locale/es-ES/LC_MESSAGES/app.po
ajenti_plugin_docker/locale/et/LC_MESSAGES/app.js
ajenti_plugin_docker/locale/et/LC_MESSAGES/app.po
ajenti_plugin_docker/locale/fa/LC_MESSAGES/app.js
ajenti_plugin_docker/locale/fa/LC_MESSAGES/app.po
ajenti_plugin_docker/locale/fi/LC_MESSAGES/app.js
ajenti_plugin_docker/locale/fi/LC_MESSAGES/app.po
ajenti_plugin_docker/locale/fr/LC_MESSAGES/app.js
