Metadata-Version: 1.2
Name: ajenti.plugin.docker
Version: 0.5
Summary: Docker
Home-page: https://ajenti.org
Author: Arnaud Kientz
Author-email: arnaud@linuxmuster.net
License: UNKNOWN
Platform: UNKNOWN
Requires-Python: >=3
